{
"type": "FeatureCollection",
"name": "BRIDG_50",
"crs": { "type": "name", "properties": { "name": "urn:ogc:def:crs:OGC:1.3:CRS84" } },
"features": [
{ "type": "Feature", "properties": { "osm_id": 8895616593, "name": null, "amenity": "bench", "man_made": null, "leisure": null, "playground": null, "memorial": null }, "geometry": { "type": "Point", "coordinates": [ -3.6740266, 51.534036 ] } },
{ "type": "Feature", "properties": { "osm_id": 8895616592, "name": null, "amenity": "bench", "man_made": null, "leisure": null, "playground": null, "memorial": null }, "geometry": { "type": "Point", "coordinates": [ -3.6740188, 51.5340639 ] } }
]
}
