{
"type": "FeatureCollection",
"name": "BRIDG_12",
"crs": { "type": "name", "properties": { "name": "urn:ogc:def:crs:OGC:1.3:CRS84" } },
"features": [
{ "type": "Feature", "properties": { "osm_id": 12444863144, "name": null, "amenity": "bench", "man_made": null, "leisure": null, "playground": null, "memorial": null }, "geometry": { "type": "Point", "coordinates": [ -3.6012068, 51.5137839 ] } },
{ "type": "Feature", "properties": { "osm_id": 12448855217, "name": null, "amenity": "bench", "man_made": null, "leisure": null, "playground": null, "memorial": null }, "geometry": { "type": "Point", "coordinates": [ -3.6009342, 51.5139147 ] } }
]
}
