{
"type": "FeatureCollection",
"name": "SWANS_54_toilets",
"crs": { "type": "name", "properties": { "name": "urn:ogc:def:crs:OGC:1.3:CRS84" } },
"features": [
{ "type": "Feature", "properties": { "name": "Cwmdonkin Park", "payment_info": "Cost unknown", "accessible": "True", "radar": "False", "women": "True", "men": "True", "baby_change": "False", "Mon": "09:00-18:00", "Tue": "09:00-18:00", "Wed": "09:00-18:00", "Thu": "09:00-18:00", "Fri": "09:00-18:00", "Sat": "09:00-18:00", "Sun": "09:00-18:00", "index_right": 84, "park_offical_id": "SWANS_54" }, "geometry": { "type": "Point", "coordinates": [ -3.971064091, 51.621633625 ] } }
]
}
