{
"type": "FeatureCollection",
"name": "SWANS_29",
"crs": { "type": "name", "properties": { "name": "urn:ogc:def:crs:OGC:1.3:CRS84" } },
"features": [
{ "type": "Feature", "properties": { "osm_id": 11835503644, "name": null, "amenity": "bench", "man_made": null, "leisure": null, "playground": null, "memorial": null }, "geometry": { "type": "Point", "coordinates": [ -3.9947357, 51.5964681 ] } },
{ "type": "Feature", "properties": { "osm_id": 11835503645, "name": null, "amenity": "bench", "man_made": null, "leisure": null, "playground": null, "memorial": null }, "geometry": { "type": "Point", "coordinates": [ -3.9945483, 51.5965762 ] } },
{ "type": "Feature", "properties": { "osm_id": 11835513682, "name": null, "amenity": "bench", "man_made": null, "leisure": null, "playground": null, "memorial": null }, "geometry": { "type": "Point", "coordinates": [ -3.9944157, 51.596731 ] } },
{ "type": "Feature", "properties": { "osm_id": 11835538429, "name": null, "amenity": "bench", "man_made": null, "leisure": null, "playground": null, "memorial": null }, "geometry": { "type": "Point", "coordinates": [ -3.9942389, 51.5969111 ] } },
{ "type": "Feature", "properties": { "osm_id": 11835513550, "name": null, "amenity": "bench", "man_made": null, "leisure": null, "playground": null, "memorial": null }, "geometry": { "type": "Point", "coordinates": [ -3.9941192, 51.597052 ] } },
{ "type": "Feature", "properties": { "osm_id": 11835519704, "name": null, "amenity": "bench", "man_made": null, "leisure": null, "playground": null, "memorial": null }, "geometry": { "type": "Point", "coordinates": [ -3.9946779, 51.5977076 ] } },
{ "type": "Feature", "properties": { "osm_id": 11835580016, "name": null, "amenity": "bench", "man_made": null, "leisure": null, "playground": null, "memorial": null }, "geometry": { "type": "Point", "coordinates": [ -3.994679, 51.5977335 ] } },
{ "type": "Feature", "properties": { "osm_id": 11835579879, "name": null, "amenity": "bench", "man_made": null, "leisure": null, "playground": null, "memorial": null }, "geometry": { "type": "Point", "coordinates": [ -3.9940694, 51.5980365 ] } },
{ "type": "Feature", "properties": { "osm_id": 11835538430, "name": null, "amenity": "bench", "man_made": null, "leisure": null, "playground": null, "memorial": null }, "geometry": { "type": "Point", "coordinates": [ -3.9941278, 51.598039 ] } }
]
}
