{
"type": "FeatureCollection",
"name": "SWANS_17",
"crs": { "type": "name", "properties": { "name": "urn:ogc:def:crs:OGC:1.3:CRS84" } },
"features": [
{ "type": "Feature", "properties": { "osm_id": 11060596706, "name": null, "amenity": "bench", "man_made": null, "leisure": null, "playground": null, "memorial": null }, "geometry": { "type": "Point", "coordinates": [ -3.9503771, 51.6165315 ] } },
{ "type": "Feature", "properties": { "osm_id": 11060594519, "name": null, "amenity": "bench", "man_made": null, "leisure": null, "playground": null, "memorial": null }, "geometry": { "type": "Point", "coordinates": [ -3.9502629, 51.6166432 ] } }
]
}
