{
"type": "FeatureCollection",
"name": "SWANS_61",
"crs": { "type": "name", "properties": { "name": "urn:ogc:def:crs:OGC:1.3:CRS84" } },
"features": [
{ "type": "Feature", "properties": { "osm_id": 9875498341, "name": null, "amenity": null, "man_made": null, "leisure": "picnic_table", "playground": null, "memorial": null }, "geometry": { "type": "Point", "coordinates": [ -4.0073131, 51.5945127 ] } },
{ "type": "Feature", "properties": { "osm_id": 9875498340, "name": null, "amenity": null, "man_made": null, "leisure": "picnic_table", "playground": null, "memorial": null }, "geometry": { "type": "Point", "coordinates": [ -4.0073158, 51.5949609 ] } },
{ "type": "Feature", "properties": { "osm_id": 9875498917, "name": null, "amenity": null, "man_made": null, "leisure": "picnic_table", "playground": null, "memorial": null }, "geometry": { "type": "Point", "coordinates": [ -3.9981971, 51.5962286 ] } }
]
}
