{
"type": "FeatureCollection",
"name": "NEAPO_37_toilets",
"crs": { "type": "name", "properties": { "name": "urn:ogc:def:crs:OGC:1.3:CRS84" } },
"features": [
{ "type": "Feature", "properties": { "name": "Unknown", "payment_info": "Cost unknown", "accessible": "False", "radar": "Unknown", "women": "Unknown", "men": "Unknown", "baby_change": "Unknown", "Mon": "Unknown", "Tue": "Unknown", "Wed": "Unknown", "Thu": "Unknown", "Fri": "Unknown", "Sat": "Unknown", "Sun": "Unknown", "index_right": 31, "park_offical_id": "NEAPO_37" }, "geometry": { "type": "Point", "coordinates": [ -3.8032108, 51.6616655 ] } },
{ "type": "Feature", "properties": { "name": "Neath Station  Platform 2 Passengers Only", "payment_info": "4", "accessible": "True", "radar": "True", "women": "True", "men": "Unknown", "baby_change": "True", "Mon": "06:00-22:00", "Tue": "06:00-22:00", "Wed": "06:00-22:00", "Thu": "06:00-22:00", "Fri": "06:00-22:00", "Sat": "06:00-22:00", "Sun": "06:00-22:00", "index_right": 31, "park_offical_id": "NEAPO_37" }, "geometry": { "type": "Point", "coordinates": [ -3.807012141, 51.662259235 ] } }
]
}
